webinstaller/__init__.py
webinstaller/webinstaller.py
webinstaller-0.0.4.dist-info/METADATA
webinstaller-0.0.4.dist-info/WHEEL
webinstaller-0.0.4.dist-info/licenses/LICENSE
webinstaller-0.0.4.dist-info/RECORD
