Metadata-Version: 2.3
Name: webinstaller
Version: 0.0.4
Summary: A Python library designed for hassle-free file downloads from Google Drive. It lets you specify the destination folder for downloads and supports .zip and .rar file formats.
Project-URL: Homepage, https://github.com/Sal0ID/webinstaller
Project-URL: Issues, https://github.com/Sal0ID/webinstaller/issues
Author-email: Sal0ID <jzqard2rv@mozmail.com>
Classifier: License :: OSI Approved :: MIT License
Classifier: Operating System :: OS Independent
Classifier: Programming Language :: Python :: 3
Requires-Python: >=3.8
Requires-Dist: bs4
Requires-Dist: py7zr
Requires-Dist: pywin32
Requires-Dist: requests
